{"name":"VIR-233.01 Verify that the customer is able to open the Support Ticket form within My Account","id":"act-8---support-tickets;vir-233.01-verify-that-the-customer-is-able-to-open-the-support-ticket-form-within-my-account","userStory":{"id":"act-8---support-tickets","storyName":"ACT-8 - Support Tickets","path":"account_management/ACT8_SupportTickets.feature","narrative":"As a shopper, I require the ability\nto file a support ticket within My Account","type":"feature"},"featureTag":{"name":"ACT-8 - Support Tickets","type":"feature"},"title":"VIR-233.01 Verify that the customer is able to open the Support Ticket form within My Account","description":"","coreIssues":["VIR-233"],"tags":[{"name":"Account management/Act 8   support tickets","type":"feature"},{"name":"pending","type":"tag"},{"name":"Account management","type":"capability"}],"startTime":1502449649688,"duration":0,"projectKey":"","annotatedResult":"PENDING","manual":false,"testSource":"Cucumber","result":"PENDING","issues":["VIR-233"]}